workon/__init__.py
workon/workon.py
workon2-0.2.dev0.data/scripts/workon.sh
workon2-0.2.dev0.dist-info/METADATA
workon2-0.2.dev0.dist-info/RECORD
workon2-0.2.dev0.dist-info/WHEEL
workon2-0.2.dev0.dist-info/entry_points.txt
workon2-0.2.dev0.dist-info/top_level.txt
