Metadata-Version: 2.1
Name: workon2
Version: 0.2.dev0
Summary: Project-management for your shell.
Home-page: https://github.com/afjlambert/workon
Author: Andre Lambert
Author-email: afj.lambert@gmail.com
License: MIT
Keywords: bash,shell,cli,pm,project management,navigation
Platform: UNKNOWN
Requires-Dist: click (==6.7)
Requires-Dist: PyYAML (==3.12)
